tbacktest/BacktestBase.py
tbacktest/BacktestLongOnly.py
tbacktest/BacktestTargetWealth.py
tbacktest/__init__.py
tbacktest-0.1.4.dist-info/METADATA
tbacktest-0.1.4.dist-info/WHEEL
tbacktest-0.1.4.dist-info/top_level.txt
tbacktest-0.1.4.dist-info/RECORD
